README
setup.py
gxml/__init__.py
gxml/base.py
gxml/elemtree.py
gxml/minidom.py
gxml.egg-info/PKG-INFO
gxml.egg-info/SOURCES.txt
gxml.egg-info/dependency_links.txt
gxml.egg-info/top_level.txt