Metadata-Version: 1.0
Name: gxml
Version: 0.3.1
Summary: A Good XML Abstraction. Provides a common interface to popular XML libaries. Currently supports elementree and minidom. Tutorials are available at www.xkenneth.com/gxml
Home-page: http://www.xkenneth.com/gxml
Author: Kenneth Miller
Author-email: xkenneth@gmail.com
License: UNKNOWN
Keywords: python xml elementtree lxml minidom xpath ironpython
Platform: UNKNOWN
